{
  "name": "Yuniel Acosta",
  "image": "/uploads/me.webp",
  "rol": "Senior Software Engineer",
  "bio": "Soy una persona muy extrovertida y curiosa, apasionado por la codificación, el espacio, la naturaleza y los deportes. Disfruto creando software asombroso, ya sean sitios web o aplicaciones. Mi objetivo es siempre producir productos que ofrezcan un alto rendimiento. Estoy interesado en nuevas oportunidades en especial en proyectos grandes y ambiciosos.",
  "email": "yunielacosta738@gmail.com",
  "lang": "es",
  "social": [
    {
      "name": "github",
      "url": "https://www.github.com/yacosta738",
      "icon": "uit:github-alt"
    },
    {
      "name": "linkedin",
      "url": "https://www.linkedin.com/in/yacosta738",
      "icon": "uit:linkedin-alt"
    },
    {
      "name": "twitter",
      "url": "https://www.twitter.com/yacosta738",
      "icon": "uit:twitter-alt"
    }
  ]
}
